<?xml version="1.0" encoding="utf-8"?>
<R Id="490031" V="0" DC="SM" EN="Office.Feedback.Survey.Deserialization.Error" ATT="d79e824386c4441cb8c1d4ae15690526-bd443309-5494-444a-aba9-0af9eef99f84-7360" DCa="PSU" xmlns="">
  <S>
    <UTS T="1" Id="9mjrl" A="9mjrk 8pgfl 9mjqt 9mjqs 8pgfe 9mjqq 9mjqp 8pgfd 7i427 9mjqo 9mjqn 8pgfc 9mjqm 9mjql 8pgfb 86t2j 86t2i 8pgfa" />
  </S>
  <C T="TAG" I="0" O="false" N="EventId">
    <S T="1" F="ULS_Tag" />
  </C>
  <C T="W" I="1" O="true" N="SurveyId">
    <S T="1" F="SurveyId" M="Ignore" />
  </C>
  <T>
    <S T="1" />
  </T>
</R>
