<?xml version="1.0" encoding="utf-8"?>
<R Id="230161" V="0" DC="SM" EN="Office.ClickToRun.MsoMigrate" ATT="0da1917aa56040d3a011c3813ca36107-76f080d8-b37f-4635-8054-5c133fcd04c4-6587" S="3" DCa="PSP" xmlns="">
  <S>
    <UTS T="1" Id="c5n43" />
    <UTS T="2" Id="c5n44" />
    <UTS T="3" Id="c5n45" />
    <UTS T="4" Id="c5n46" />
    <US T="5">
      <S T="1" />
      <S T="2" />
      <S T="3" />
      <S T="4" />
    </US>
  </S>
  <C T="TAG" I="0" O="true" N="EventID">
    <S T="5" F="ULS_Tag" M="Ignore" />
  </C>
  <T>
    <S T="5" />
  </T>
</R>
